cem/CEM.py
cem/__init__.py
cem/examples.py
cross_entropy_method/CEM.py
cross_entropy_method/__init__.py
cross_entropy_method/examples.py
cross_entropy_method-0.1.1.dist-info/LICENSE
cross_entropy_method-0.1.1.dist-info/METADATA
cross_entropy_method-0.1.1.dist-info/WHEEL
cross_entropy_method-0.1.1.dist-info/top_level.txt
cross_entropy_method-0.1.1.dist-info/RECORD
