Metadata-Version: 2.1
Name: cross-entropy-method
Version: 0.1.1
Summary: The Cross-Entropy Method for either rare-event sampling or optimization.
Home-page: https://github.com/ido90/CEM
Author: Ido Greenberg
License: MIT
Keywords: cross entropy,CEM,sampling,optimization
Platform: UNKNOWN
Classifier: License :: OSI Approved :: MIT License
Classifier: Programming Language :: Python :: 3
Requires-Python: >=3.5
License-File: LICENSE
Requires-Dist: numpy
Requires-Dist: scipy
Requires-Dist: pandas
